LICENSE
README.md
setup.cfg
setup.py
saphires/__init__.py
saphires/bf.py
saphires/io.py
saphires/utils.py
saphires/xc.py
saphires.egg-info/PKG-INFO
saphires.egg-info/SOURCES.txt
saphires.egg-info/dependency_links.txt
saphires.egg-info/top_level.txt
saphires/extras/__init__.py
saphires/extras/bspline_acr.py